dynalist_to_md/__init__.py
dynalist_to_md/__main__.py
dynalist_to_md/convert_to_md.py
dynalist_to_md_joegnis-0.1.dev1.dist-info/LICENSE
dynalist_to_md_joegnis-0.1.dev1.dist-info/METADATA
dynalist_to_md_joegnis-0.1.dev1.dist-info/WHEEL
dynalist_to_md_joegnis-0.1.dev1.dist-info/entry_points.txt
dynalist_to_md_joegnis-0.1.dev1.dist-info/top_level.txt
dynalist_to_md_joegnis-0.1.dev1.dist-info/RECORD
