Metadata-Version: 2.1
Name: dynalist-to-md-joegnis
Version: 0.1.dev1
Summary: A tool that converts text exported fromDynalist into Markdown text
Home-page: https://github.com/joegnis/dynalist-to-markdown
Author: joegnis
Author-email: joegnis@pm.me
License: UNKNOWN
Platform: UNKNOWN
Classifier: Programming Language :: Python :: 3
Classifier: License :: OSI Approved :: MIT License
Classifier: Operating System :: OS Independent
Requires-Python: >=3.7
